certauth2/__init__.py
certauth2/__main__.py
certauth2/creds_store.py
certauth2/store.py
certauth2/utils.py
certauth2-0.4.2.dist-info/METADATA
certauth2-0.4.2.dist-info/WHEEL
certauth2-0.4.2.dist-info/top_level.txt
certauth2-0.4.2.dist-info/RECORD
