Metadata-Version: 2.1
Name: certauth2
Version: 0.4.2
Summary: CertAuth remake that works based on cryptography with minimal deps and advanced functions for credentials output and issuer ca input
Home-page: https://github.com/jose-pr/pypki
Author: Jose A.
Author-email: jose-pr@coqui.dev
License: UNKNOWN
Platform: UNKNOWN
Requires-Dist: x509creds (>=0.10.0)
Requires-Dist: tld ; extra == "tld"
